{ "Address": "0x41894e", "Opcode": "ff95ef030000", "Opcodesize": 6, "Mnemonic": "call dword ptr [ebp + 0x3ef]", "PID": 1712, "TID": 1768, "Arguments": [ "Arg1", "IN", "HMODULE", "0x18ff5c", "0x400000", "Arg2", "OUT", "LPTSTR", "0x18ff60", "0x418000", "Arg3", "IN", "DWORD", "0x18ff64", "0x104" ], "Timesptamp": "00000001.143860", "FunctionName": "GetModuleFileNameA", "ModuleName": "kernel32.dll", "Return": "0x1f", "Output1": [ "0x418000", "C:\\Users\\lhs\\Exec\\telock_7z.exe" ], "Status": 0 }
{ "Address": "0x418996", "Opcode": "ff95eb030000", "Opcodesize": 6, "Mnemonic": "call dword ptr [ebp + 0x3eb]", "PID": 1712, "TID": 1768, "Arguments": [ "Arg1", "IN", "LPCTSTR", "0x18ff50", "C:\\Users\\lhs\\Exec\\telock_7z.exe", "Arg2", "IN", "DWORD", "0x18ff54", "0x80000000", "Arg3", "IN", "DWORD", "0x18ff58", "0x1", "Arg4", "IN", "LPSECURITY_ATTRIBUTES", "0x18ff5c", "0x0", "Arg5", "IN", "DWORD", "0x18ff60", "0x3", "Arg6", "IN", "DWORD", "0x18ff64", "0x80", "Arg7", "IN", "HANDLE", "0x18ff68", "0x0" ], "Timesptamp": "00000001.174469", "FunctionName": "CreateFileA", "ModuleName": "kernel32.dll", "Return": "0x60", "Status": 0 }
{ "Address": "0x4189a3", "Opcode": "ff95e7030000", "Opcodesize": 6, "Mnemonic": "call dword ptr [ebp + 0x3e7]", "PID": 1712, "TID": 1768, "Arguments": [ "Arg1", "IN", "HANDLE", "0x18ff54", "0x60", "Arg2", "OUT", "LPVOID", "0x18ff58", "0x418008", "Arg3", "IN", "DWORD", "0x18ff5c", "0x400", "Arg4", "OUT", "LPDWORD", "0x18ff60", "0x418000", "Arg5", "OUT", "LPOVERLAPPED", "0x18ff64", "0x0" ], "Timesptamp": "00000001.204127", "FunctionName": "ReadFile", "ModuleName": "kernel32.dll", "Return": "TRUE", "Output1": [ "0x418008", "0x905a4d" ], "Output2": [ "0x418000", "0x400" ], "Status": 0 }
{ "Address": "0x4189a9", "Opcode": "ff95e3030000", "Opcodesize": 6, "Mnemonic": "call dword ptr [ebp + 0x3e3]", "PID": 1712, "TID": 1768, "Arguments": [ "Arg1", "IN", "HANDLE", "0x18ff68", "0x60" ], "Timesptamp": "00000001.235153", "FunctionName": "CloseHandle", "ModuleName": "kernel32.dll", "Return": "TRUE", "Status": 0 }
{ "Address": "0x418ca0", "Opcode": "ff95f4ba4000", "Opcodesize": 6, "Mnemonic": "call dword ptr [ebp + 0x40baf4]", "PID": 1712, "TID": 1768, "Arguments": [ "Arg1", "IN", "LPSECURITY_ATTRIBUTES", "0x18ff60", "0x0", "Arg2", "IN", "BOOL", "0x18ff64", "TRUE", "Arg3", "IN", "LPCSTR", "0x18ff68", "uMYxP9u8" ], "Timesptamp": "00000001.365465", "FunctionName": "CreateMutexA", "ModuleName": "kernel32.dll", "Return": "0x64", "Status": 0 }
{ "Address": "0x419087", "Opcode": "ff95ecba4000", "Opcodesize": 6, "Mnemonic": "call dword ptr [ebp + 0x40baec]", "PID": 1712, "TID": 1768, "Arguments": [ "Arg1", "IN", "LPVOID", "0x18ff30", "0x0", "Arg2", "IN", "SIZE_T", "0x18ff34", "0x8a10", "Arg3", "IN", "DWORD", "0x18ff38", "0x1000", "Arg4", "IN", "DWORD", "0x18ff3c", "0x4" ], "Timesptamp": "00000001.460064", "FunctionName": "VirtualAlloc", "ModuleName": "kernel32.dll", "Return": "0x230000", "Status": 0 }
{ "Address": "0x419159", "Opcode": "ff95f0ba4000", "Opcodesize": 6, "Mnemonic": "call dword ptr [ebp + 0x40baf0]", "PID": 1712, "TID": 1768, "Arguments": [ "Arg1", "IN", "LPVOID", "0x18ff34", "0x230000", "Arg2", "IN", "SIZE_T", "0x18ff38", "0x8a10", "Arg3", "IN", "DWORD", "0x18ff3c", "0x4000" ], "Timesptamp": "00000001.490698", "FunctionName": "VirtualFree", "ModuleName": "kernel32.dll", "Return": "TRUE", "Status": 0 }
{ "Address": "0x419087", "Opcode": "ff95ecba4000", "Opcodesize": 6, "Mnemonic": "call dword ptr [ebp + 0x40baec]", "PID": 1712, "TID": 1768, "Arguments": [ "Arg1", "IN", "LPVOID", "0x18ff30", "0x0", "Arg2", "IN", "SIZE_T", "0x18ff34", "0x1010", "Arg3", "IN", "DWORD", "0x18ff38", "0x1000", "Arg4", "IN", "DWORD", "0x18ff3c", "0x4" ], "Timesptamp": "00000001.518190", "FunctionName": "VirtualAlloc", "ModuleName": "kernel32.dll", "Return": "0x240000", "Status": 0 }
{ "Address": "0x419159", "Opcode": "ff95f0ba4000", "Opcodesize": 6, "Mnemonic": "call dword ptr [ebp + 0x40baf0]", "PID": 1712, "TID": 1768, "Arguments": [ "Arg1", "IN", "LPVOID", "0x18ff34", "0x240000", "Arg2", "IN", "SIZE_T", "0x18ff38", "0x1010", "Arg3", "IN", "DWORD", "0x18ff3c", "0x4000" ], "Timesptamp": "00000001.548923", "FunctionName": "VirtualFree", "ModuleName": "kernel32.dll", "Return": "TRUE", "Status": 0 }
{ "Address": "0x419087", "Opcode": "ff95ecba4000", "Opcodesize": 6, "Mnemonic": "call dword ptr [ebp + 0x40baec]", "PID": 1712, "TID": 1768, "Arguments": [ "Arg1", "IN", "LPVOID", "0x18ff30", "0x0", "Arg2", "IN", "SIZE_T", "0x18ff34", "0xa10", "Arg3", "IN", "DWORD", "0x18ff38", "0x1000", "Arg4", "IN", "DWORD", "0x18ff3c", "0x4" ], "Timesptamp": "00000001.578148", "FunctionName": "VirtualAlloc", "ModuleName": "kernel32.dll", "Return": "0x2d0000", "Status": 0 }
{ "Address": "0x419159", "Opcode": "ff95f0ba4000", "Opcodesize": 6, "Mnemonic": "call dword ptr [ebp + 0x40baf0]", "PID": 1712, "TID": 1768, "Arguments": [ "Arg1", "IN", "LPVOID", "0x18ff34", "0x2d0000", "Arg2", "IN", "SIZE_T", "0x18ff38", "0xa10", "Arg3", "IN", "DWORD", "0x18ff3c", "0x4000" ], "Timesptamp": "00000001.610019", "FunctionName": "VirtualFree", "ModuleName": "kernel32.dll", "Return": "TRUE", "Status": 0 }
{ "Address": "0x419241", "Opcode": "ff95d0d24000", "Opcodesize": 6, "Mnemonic": "call dword ptr [ebp + 0x40d2d0]", "PID": 1712, "TID": 1768, "Arguments": [ "Arg1", "IN", "LPCTSTR", "0x18ff68", "KERNEL32.dll" ], "Timesptamp": "00000001.641012", "FunctionName": "GetModuleHandleA", "ModuleName": "kernel32.dll", "Return": "0x74f10000", "Status": 0 }
{ "Address": "0x419416", "Opcode": "ff95ecba4000", "Opcodesize": 6, "Mnemonic": "call dword ptr [ebp + 0x40baec]", "PID": 1712, "TID": 1768, "Arguments": [ "Arg1", "IN", "LPVOID", "0x18ff3c", "0x0", "Arg2", "IN", "SIZE_T", "0x18ff40", "0xb4b", "Arg3", "IN", "DWORD", "0x18ff44", "0x1000", "Arg4", "IN", "DWORD", "0x18ff48", "0x4" ], "Timesptamp": "00000001.671393", "FunctionName": "VirtualAlloc", "ModuleName": "kernel32.dll", "Return": "0x2e0000", "Status": 0 }
{ "Address": "0x419574", "Opcode": "ff95e0ba4000", "Opcodesize": 6, "Mnemonic": "call dword ptr [ebp + 0x40bae0]", "PID": 1712, "TID": 1768, "Arguments": [ "Arg1", "IN", "HMODULE", "0x18ff60", "0x74f10000", "Arg2", "IN", "LPCSTR", "0x18ff64", "FreeLibrary" ], "Timesptamp": "00000001.697058", "FunctionName": "GetProcAddress", "ModuleName": "kernel32.dll", "Return": "0x74f234c8", "Status": 0 }
{ "Address": "0x419574", "Opcode": "ff95e0ba4000", "Opcodesize": 6, "Mnemonic": "call dword ptr [ebp + 0x40bae0]", "PID": 1712, "TID": 1768, "Arguments": [ "Arg1", "IN", "HMODULE", "0x18ff60", "0x74f10000", "Arg2", "IN", "LPCSTR", "0x18ff64", "LoadLibraryExA" ], "Timesptamp": "00000001.722164", "FunctionName": "GetProcAddress", "ModuleName": "kernel32.dll", "Return": "0x74f24913", "Status": 0 }
{ "Address": "0x419574", "Opcode": "ff95e0ba4000", "Opcodesize": 6, "Mnemonic": "call dword ptr [ebp + 0x40bae0]", "PID": 1712, "TID": 1768, "Arguments": [ "Arg1", "IN", "HMODULE", "0x18ff60", "0x74f10000", "Arg2", "IN", "LPCSTR", "0x18ff64", "LoadLibraryA" ], "Timesptamp": "00000001.750059", "FunctionName": "GetProcAddress", "ModuleName": "kernel32.dll", "Return": "0x74f249d7", "Status": 0 }
{ "Address": "0x419574", "Opcode": "ff95e0ba4000", "Opcodesize": 6, "Mnemonic": "call dword ptr [ebp + 0x40bae0]", "PID": 1712, "TID": 1768, "Arguments": [ "Arg1", "IN", "HMODULE", "0x18ff60", "0x74f10000", "Arg2", "IN", "LPCSTR", "0x18ff64", "LoadLibraryExW" ], "Timesptamp": "00000001.781101", "FunctionName": "GetProcAddress", "ModuleName": "kernel32.dll", "Return": "0x74f2495d", "Status": 0 }
{ "Address": "0x419574", "Opcode": "ff95e0ba4000", "Opcodesize": 6, "Mnemonic": "call dword ptr [ebp + 0x40bae0]", "PID": 1712, "TID": 1768, "Arguments": [ "Arg1", "IN", "HMODULE", "0x18ff60", "0x74f10000", "Arg2", "IN", "LPCSTR", "0x18ff64", "LoadLibraryW" ], "Timesptamp": "00000001.812386", "FunctionName": "GetProcAddress", "ModuleName": "kernel32.dll", "Return": "0x74f2492b", "Status": 0 }
{ "Address": "0x419574", "Opcode": "ff95e0ba4000", "Opcodesize": 6, "Mnemonic": "call dword ptr [ebp + 0x40bae0]", "PID": 1712, "TID": 1768, "Arguments": [ "Arg1", "IN", "HMODULE", "0x18ff60", "0x74f10000", "Arg2", "IN", "LPCSTR", "0x18ff64", "GetModuleFileNameA" ], "Timesptamp": "00000001.843006", "FunctionName": "GetProcAddress", "ModuleName": "kernel32.dll", "Return": "0x74f214b1", "Status": 0 }
{ "Address": "0x419574", "Opcode": "ff95e0ba4000", "Opcodesize": 6, "Mnemonic": "call dword ptr [ebp + 0x40bae0]", "PID": 1712, "TID": 1768, "Arguments": [ "Arg1", "IN", "HMODULE", "0x18ff60", "0x74f10000", "Arg2", "IN", "LPCSTR", "0x18ff64", "GetProcAddress" ], "Timesptamp": "00000001.876918", "FunctionName": "GetProcAddress", "ModuleName": "kernel32.dll", "Return": "0x74f21222", "Status": 0 }
{ "Address": "0x419574", "Opcode": "ff95e0ba4000", "Opcodesize": 6, "Mnemonic": "call dword ptr [ebp + 0x40bae0]", "PID": 1712, "TID": 1768, "Arguments": [ "Arg1", "IN", "HMODULE", "0x18ff60", "0x74f10000", "Arg2", "IN", "LPCSTR", "0x18ff64", "GetModuleFileNameW" ], "Timesptamp": "00000001.914735", "FunctionName": "GetProcAddress", "ModuleName": "kernel32.dll", "Return": "0x74f24950", "Status": 0 }
{ "Address": "0x419574", "Opcode": "ff95e0ba4000", "Opcodesize": 6, "Mnemonic": "call dword ptr [ebp + 0x40bae0]", "PID": 1712, "TID": 1768, "Arguments": [ "Arg1", "IN", "HMODULE", "0x18ff60", "0x74f10000", "Arg2", "IN", "LPCSTR", "0x18ff64", "LocalFree" ], "Timesptamp": "00000001.939580", "FunctionName": "GetProcAddress", "ModuleName": "kernel32.dll", "Return": "0x74f22d3c", "Status": 0 }
{ "Address": "0x419574", "Opcode": "ff95e0ba4000", "Opcodesize": 6, "Mnemonic": "call dword ptr [ebp + 0x40bae0]", "PID": 1712, "TID": 1768, "Arguments": [ "Arg1", "IN", "HMODULE", "0x18ff60", "0x74f10000", "Arg2", "IN", "LPCSTR", "0x18ff64", "FormatMessageA" ], "Timesptamp": "00000001.969155", "FunctionName": "GetProcAddress", "ModuleName": "kernel32.dll", "Return": "0x74f45fbd", "Status": 0 }
{ "Address": "0x419574", "Opcode": "ff95e0ba4000", "Opcodesize": 6, "Mnemonic": "call dword ptr [ebp + 0x40bae0]", "PID": 1712, "TID": 1768, "Arguments": [ "Arg1", "IN", "HMODULE", "0x18ff60", "0x74f10000", "Arg2", "IN", "LPCSTR", "0x18ff64", "FormatMessageW" ], "Timesptamp": "00000001.989808", "FunctionName": "GetProcAddress", "ModuleName": "kernel32.dll", "Return": "0x74f24620", "Status": 0 }
{ "Address": "0x419574", "Opcode": "ff95e0ba4000", "Opcodesize": 6, "Mnemonic": "call dword ptr [ebp + 0x40bae0]", "PID": 1712, "TID": 1768, "Arguments": [ "Arg1", "IN", "HMODULE", "0x18ff60", "0x74f10000", "Arg2", "IN", "LPCSTR", "0x18ff64", "SetFileAttributesA" ], "Timesptamp": "00000002.017012", "FunctionName": "GetProcAddress", "ModuleName": "kernel32.dll", "Return": "0x74f3ecd3", "Status": 0 }
{ "Address": "0x419574", "Opcode": "ff95e0ba4000", "Opcodesize": 6, "Mnemonic": "call dword ptr [ebp + 0x40bae0]", "PID": 1712, "TID": 1768, "Arguments": [ "Arg1", "IN", "HMODULE", "0x18ff60", "0x74f10000", "Arg2", "IN", "LPCSTR", "0x18ff64", "SetFileAttributesW" ], "Timesptamp": "00000002.048279", "FunctionName": "GetProcAddress", "ModuleName": "kernel32.dll", "Return": "0x74f3d4f7", "Status": 0 }
{ "Address": "0x419574", "Opcode": "ff95e0ba4000", "Opcodesize": 6, "Mnemonic": "call dword ptr [ebp + 0x40bae0]", "PID": 1712, "TID": 1768, "Arguments": [ "Arg1", "IN", "HMODULE", "0x18ff60", "0x74f10000", "Arg2", "IN", "LPCSTR", "0x18ff64", "RemoveDirectoryA" ], "Timesptamp": "00000002.077191", "FunctionName": "GetProcAddress", "ModuleName": "kernel32.dll", "Return": "0x74fa44bf", "Status": 0 }
{ "Address": "0x419574", "Opcode": "ff95e0ba4000", "Opcodesize": 6, "Mnemonic": "call dword ptr [ebp + 0x40bae0]", "PID": 1712, "TID": 1768, "Arguments": [ "Arg1", "IN", "HMODULE", "0x18ff60", "0x74f10000", "Arg2", "IN", "LPCSTR", "0x18ff64", "RemoveDirectoryW" ], "Timesptamp": "00000002.097050", "FunctionName": "GetProcAddress", "ModuleName": "kernel32.dll", "Return": "0x74fa44cf", "Status": 0 }
{ "Address": "0x419574", "Opcode": "ff95e0ba4000", "Opcodesize": 6, "Mnemonic": "call dword ptr [ebp + 0x40bae0]", "PID": 1712, "TID": 1768, "Arguments": [ "Arg1", "IN", "HMODULE", "0x18ff60", "0x74f10000", "Arg2", "IN", "LPCSTR", "0x18ff64", "MoveFileA" ], "Timesptamp": "00000002.124392", "FunctionName": "GetProcAddress", "ModuleName": "kernel32.dll", "Return": "0x74f9d911", "Status": 0 }
{ "Address": "0x419574", "Opcode": "ff95e0ba4000", "Opcodesize": 6, "Mnemonic": "call dword ptr [ebp + 0x40bae0]", "PID": 1712, "TID": 1768, "Arguments": [ "Arg1", "IN", "HMODULE", "0x18ff60", "0x74f10000", "Arg2", "IN", "LPCSTR", "0x18ff64", "MoveFileW" ], "Timesptamp": "00000002.154940", "FunctionName": "GetProcAddress", "ModuleName": "kernel32.dll", "Return": "0x74f39af0", "Status": 0 }
{ "Address": "0x419574", "Opcode": "ff95e0ba4000", "Opcodesize": 6, "Mnemonic": "call dword ptr [ebp + 0x40bae0]", "PID": 1712, "TID": 1768, "Arguments": [ "Arg1", "IN", "HMODULE", "0x18ff60", "0x74f10000", "Arg2", "IN", "LPCSTR", "0x18ff64", "CreateDirectoryA" ], "Timesptamp": "00000002.185529", "FunctionName": "GetProcAddress", "ModuleName": "kernel32.dll", "Return": "0x74f4d526", "Status": 0 }
{ "Address": "0x419574", "Opcode": "ff95e0ba4000", "Opcodesize": 6, "Mnemonic": "call dword ptr [ebp + 0x40bae0]", "PID": 1712, "TID": 1768, "Arguments": [ "Arg1", "IN", "HMODULE", "0x18ff60", "0x74f10000", "Arg2", "IN", "LPCSTR", "0x18ff64", "Crea" ], "Timesptamp": "00000002.216915", "FunctionName": "GetProcAddress", "ModuleName": "kernel32.dll", "Return": "0x74f24259", "Status": 0 }
{ "Address": "0x419574", "Opcode": "ff95e0ba4000", "Opcodesize": 6, "Mnemonic": "call dword ptr [ebp + 0x40bae0]", "PID": 1712, "TID": 1768, "Arguments": [ "Arg1", "IN", "HMODULE", "0x18ff60", "0x74f10000", "Arg2", "IN", "LPCSTR", "0x18ff64", "DeleteFileA" ], "Timesptamp": "00000002.247978", "FunctionName": "GetProcAddress", "ModuleName": "kernel32.dll", "Return": "0x74f25444", "Status": 0 }
{ "Address": "0x419574", "Opcode": "ff95e0ba4000", "Opcodesize": 6, "Mnemonic": "call dword ptr [ebp + 0x40bae0]", "PID": 1712, "TID": 1768, "Arguments": [ "Arg1", "IN", "HMODULE", "0x18ff60", "0x74f10000", "Arg2", "IN", "LPCSTR", "0x18ff64", "DeleteFileW" ], "Timesptamp": "00000002.267948", "FunctionName": "GetProcAddress", "ModuleName": "kernel32.dll", "Return": "0x74f289b3", "Status": 0 }
{ "Address": "0x419574", "Opcode": "ff95e0ba4000", "Opcodesize": 6, "Mnemonic": "call dword ptr [ebp + 0x40bae0]", "PID": 1712, "TID": 1768, "Arguments": [ "Arg1", "IN", "HMODULE", "0x18ff60", "0x74f10000", "Arg2", "IN", "LPCSTR", "0x18ff64", "GetFullPathNameA" ], "Timesptamp": "00000002.285263", "FunctionName": "GetProcAddress", "ModuleName": "kernel32.dll", "Return": "0x74f2e2c1", "Status": 0 }
{ "Address": "0x419574", "Opcode": "ff95e0ba4000", "Opcodesize": 6, "Mnemonic": "call dword ptr [ebp + 0x40bae0]", "PID": 1712, "TID": 1768, "Arguments": [ "Arg1", "IN", "HMODULE", "0x18ff60", "0x74f10000", "Arg2", "IN", "LPCSTR", "0x18ff64", "GetFullPathNameW" ], "Timesptamp": "00000002.310092", "FunctionName": "GetProcAddress", "ModuleName": "kernel32.dll", "Return": "0x74f240d4", "Status": 0 }
{ "Address": "0x419574", "Opcode": "ff95e0ba4000", "Opcodesize": 6, "Mnemonic": "call dword ptr [ebp + 0x40bae0]", "PID": 1712, "TID": 1768, "Arguments": [ "Arg1", "IN", "HMODULE", "0x18ff60", "0x74f10000", "Arg2", "IN", "LPCSTR", "0x18ff64", "lstrcatA" ], "Timesptamp": "00000002.341678", "FunctionName": "GetProcAddress", "ModuleName": "kernel32.dll", "Return": "0x74f42b7a", "Status": 0 }
{ "Address": "0x419574", "Opcode": "ff95e0ba4000", "Opcodesize": 6, "Mnemonic": "call dword ptr [ebp + 0x40bae0]", "PID": 1712, "TID": 1768, "Arguments": [ "Arg1", "IN", "HMODULE", "0x18ff60", "0x74f10000", "Arg2", "IN", "LPCSTR", "0x18ff64", "lstrlenA" ], "Timesptamp": "00000002.372544", "FunctionName": "GetProcAddress", "ModuleName": "kernel32.dll", "Return": "0x74f25a4b", "Status": 0 }
{ "Address": "0x419574", "Opcode": "ff95e0ba4000", "Opcodesize": 6, "Mnemonic": "call dword ptr [ebp + 0x40bae0]", "PID": 1712, "TID": 1768, "Arguments": [ "Arg1", "IN", "HMODULE", "0x18ff60", "0x74f10000", "Arg2", "IN", "LPCSTR", "0x18ff64", "GetTempPathA" ], "Timesptamp": "00000002.403836", "FunctionName": "GetProcAddress", "ModuleName": "kernel32.dll", "Return": "0x74f4276c", "Status": 0 }
{ "Address": "0x419574", "Opcode": "ff95e0ba4000", "Opcodesize": 6, "Mnemonic": "call dword ptr [ebp + 0x40bae0]", "PID": 1712, "TID": 1768, "Arguments": [ "Arg1", "IN", "HMODULE", "0x18ff60", "0x74f10000", "Arg2", "IN", "LPCSTR", "0x18ff64", "GetTempPathW" ], "Timesptamp": "00000002.434902", "FunctionName": "GetProcAddress", "ModuleName": "kernel32.dll", "Return": "0x74f3d4dc", "Status": 0 }
{ "Address": "0x419574", "Opcode": "ff95e0ba4000", "Opcodesize": 6, "Mnemonic": "call dword ptr [ebp + 0x40bae0]", "PID": 1712, "TID": 1768, "Arguments": [ "Arg1", "IN", "HMODULE", "0x18ff60", "0x74f10000", "Arg2", "IN", "LPCSTR", "0x18ff64", "GetTempFileNameA" ], "Timesptamp": "00000002.466213", "FunctionName": "GetProcAddress", "ModuleName": "kernel32.dll", "Return": "0x74f49d3f", "Status": 0 }
{ "Address": "0x419574", "Opcode": "ff95e0ba4000", "Opcodesize": 6, "Mnemonic": "call dword ptr [ebp + 0x40bae0]", "PID": 1712, "TID": 1768, "Arguments": [ "Arg1", "IN", "HMODULE", "0x18ff60", "0x74f10000", "Arg2", "IN", "LPCSTR", "0x18ff64", "GetTempFileNameW" ], "Timesptamp": "00000002.497395", "FunctionName": "GetProcAddress", "ModuleName": "kernel32.dll", "Return": "0x74f4d1b6", "Status": 0 }
{ "Address": "0x419574", "Opcode": "ff95e0ba4000", "Opcodesize": 6, "Mnemonic": "call dword ptr [ebp + 0x40bae0]", "PID": 1712, "TID": 1768, "Arguments": [ "Arg1", "IN", "HMODULE", "0x18ff60", "0x74f10000", "Arg2", "IN", "LPCSTR", "0x18ff64", "FindClose" ], "Timesptamp": "00000002.528604", "FunctionName": "GetProcAddress", "ModuleName": "kernel32.dll", "Return": "0x74f24442", "Status": 0 }
{ "Address": "0x419574", "Opcode": "ff95e0ba4000", "Opcodesize": 6, "Mnemonic": "call dword ptr [ebp + 0x40bae0]", "PID": 1712, "TID": 1768, "Arguments": [ "Arg1", "IN", "HMODULE", "0x18ff60", "0x74f10000", "Arg2", "IN", "LPCSTR", "0x18ff64", "FindFirstFileA" ], "Timesptamp": "00000002.559880", "FunctionName": "GetProcAddress", "ModuleName": "kernel32.dll", "Return": "0x74f2e2ce", "Status": 0 }
{ "Address": "0x419574", "Opcode": "ff95e0ba4000", "Opcodesize": 6, "Mnemonic": "call dword ptr [ebp + 0x40bae0]", "PID": 1712, "TID": 1768, "Arguments": [ "Arg1", "IN", "HMODULE", "0x18ff60", "0x74f10000", "Arg2", "IN", "LPCSTR", "0x18ff64", "FindFirstFileW" ], "Timesptamp": "00000002.591014", "FunctionName": "GetProcAddress", "ModuleName": "kernel32.dll", "Return": "0x74f24435", "Status": 0 }
{ "Address": "0x419574", "Opcode": "ff95e0ba4000", "Opcodesize": 6, "Mnemonic": "call dword ptr [ebp + 0x40bae0]", "PID": 1712, "TID": 1768, "Arguments": [ "Arg1", "IN", "HMODULE", "0x18ff60", "0x74f10000", "Arg2", "IN", "LPCSTR", "0x18ff64", "SetLastError" ], "Timesptamp": "00000002.622218", "FunctionName": "GetProcAddress", "ModuleName": "kernel32.dll", "Return": "0x74f211a9", "Status": 0 }
{ "Address": "0x419574", "Opcode": "ff95e0ba4000", "Opcodesize": 6, "Mnemonic": "call dword ptr [ebp + 0x40bae0]", "PID": 1712, "TID": 1768, "Arguments": [ "Arg1", "IN", "HMODULE", "0x18ff60", "0x74f10000", "Arg2", "IN", "LPCSTR", "0x18ff64", "FindNextFileA" ], "Timesptamp": "00000002.653643", "FunctionName": "GetProcAddress", "ModuleName": "kernel32.dll", "Return": "0x74f4d53e", "Status": 0 }
{ "Address": "0x419574", "Opcode": "ff95e0ba4000", "Opcodesize": 6, "Mnemonic": "call dword ptr [ebp + 0x40bae0]", "PID": 1712, "TID": 1768, "Arguments": [ "Arg1", "IN", "HMODULE", "0x18ff60", "0x74f10000", "Arg2", "IN", "LPCSTR", "0x18ff64", "FindNextFileW" ], "Timesptamp": "00000002.682679", "FunctionName": "GetProcAddress", "ModuleName": "kernel32.dll", "Return": "0x74f254ee", "Status": 0 }
{ "Address": "0x419574", "Opcode": "ff95e0ba4000", "Opcodesize": 6, "Mnemonic": "call dword ptr [ebp + 0x40bae0]", "PID": 1712, "TID": 1768, "Arguments": [ "Arg1", "IN", "HMODULE", "0x18ff60", "0x74f10000", "Arg2", "IN", "LPCSTR", "0x18ff64", "CreateFileA" ], "Timesptamp": "00000002.703730", "FunctionName": "GetProcAddress", "ModuleName": "kernel32.dll", "Return": "0x74f253c6", "Status": 0 }
{ "Address": "0x419574", "Opcode": "ff95e0ba4000", "Opcodesize": 6, "Mnemonic": "call dword ptr [ebp + 0x40bae0]", "PID": 1712, "TID": 1768, "Arguments": [ "Arg1", "IN", "HMODULE", "0x18ff60", "0x74f10000", "Arg2", "IN", "LPCSTR", "0x18ff64", "CreateFileW" ], "Timesptamp": "00000002.732284", "FunctionName": "GetProcAddress", "ModuleName": "kernel32.dll", "Return": "0x74f23f5c", "Status": 0 }
{ "Address": "0x419574", "Opcode": "ff95e0ba4000", "Opcodesize": 6, "Mnemonic": "call dword ptr [ebp + 0x40bae0]", "PID": 1712, "TID": 1768, "Arguments": [ "Arg1", "IN", "HMODULE", "0x18ff60", "0x74f10000", "Arg2", "IN", "LPCSTR", "0x18ff64", "CloseHandle" ], "Timesptamp": "00000002.762659", "FunctionName": "GetProcAddress", "ModuleName": "kernel32.dll", "Return": "0x74f21410", "Status": 0 }
{ "Address": "0x419574", "Opcode": "ff95e0ba4000", "Opcodesize": 6, "Mnemonic": "call dword ptr [ebp + 0x40bae0]", "PID": 1712, "TID": 1768, "Arguments": [ "Arg1", "IN", "HMODULE", "0x18ff60", "0x74f10000", "Arg2", "IN", "LPCSTR", "0x18ff64", "GetFileSize" ], "Timesptamp": "00000002.793783", "FunctionName": "GetProcAddress", "ModuleName": "kernel32.dll", "Return": "0x74f2196e", "Status": 0 }
{ "Address": "0x419574", "Opcode": "ff95e0ba4000", "Opcodesize": 6, "Mnemonic": "call dword ptr [ebp + 0x40bae0]", "PID": 1712, "TID": 1768, "Arguments": [ "Arg1", "IN", "HMODULE", "0x18ff60", "0x74f10000", "Arg2", "IN", "LPCSTR", "0x18ff64", "SetFilePointer" ], "Timesptamp": "00000002.818038", "FunctionName": "GetProcAddress", "ModuleName": "kernel32.dll", "Return": "0x74f217d1", "Status": 0 }
{ "Address": "0x419574", "Opcode": "ff95e0ba4000", "Opcodesize": 6, "Mnemonic": "call dword ptr [ebp + 0x40bae0]", "PID": 1712, "TID": 1768, "Arguments": [ "Arg1", "IN", "HMODULE", "0x18ff60", "0x74f10000", "Arg2", "IN", "LPCSTR", "0x18ff64", "ReadFile" ], "Timesptamp": "00000002.843934", "FunctionName": "GetProcAddress", "ModuleName": "kernel32.dll", "Return": "0x74f23ed3", "Status": 0 }
{ "Address": "0x419574", "Opcode": "ff95e0ba4000", "Opcodesize": 6, "Mnemonic": "call dword ptr [ebp + 0x40bae0]", "PID": 1712, "TID": 1768, "Arguments": [ "Arg1", "IN", "HMODULE", "0x18ff60", "0x74f10000", "Arg2", "IN", "LPCSTR", "0x18ff64", "SetFileTime" ], "Timesptamp": "00000002.872568", "FunctionName": "GetProcAddress", "ModuleName": "kernel32.dll", "Return": "0x74f3ecbb", "Status": 0 }
{ "Address": "0x419574", "Opcode": "ff95e0ba4000", "Opcodesize": 6, "Mnemonic": "call dword ptr [ebp + 0x40bae0]", "PID": 1712, "TID": 1768, "Arguments": [ "Arg1", "IN", "HMODULE", "0x18ff60", "0x74f10000", "Arg2", "IN", "LPCSTR", "0x18ff64", "WriteFile" ], "Timesptamp": "00000002.906562", "FunctionName": "GetProcAddress", "ModuleName": "kernel32.dll", "Return": "0x74f21282", "Status": 0 }
{ "Address": "0x419574", "Opcode": "ff95e0ba4000", "Opcodesize": 6, "Mnemonic": "call dword ptr [ebp + 0x40bae0]", "PID": 1712, "TID": 1768, "Arguments": [ "Arg1", "IN", "HMODULE", "0x18ff60", "0x74f10000", "Arg2", "IN", "LPCSTR", "0x18ff64", "SetEndOfFile" ], "Timesptamp": "00000002.934979", "FunctionName": "GetProcAddress", "ModuleName": "kernel32.dll", "Return": "0x74f3ce2e", "Status": 0 }
{ "Address": "0x419574", "Opcode": "ff95e0ba4000", "Opcodesize": 6, "Mnemonic": "call dword ptr [ebp + 0x40bae0]", "PID": 1712, "TID": 1768, "Arguments": [ "Arg1", "IN", "HMODULE", "0x18ff60", "0x74f10000", "Arg2", "IN", "LPCSTR", "0x18ff64", "CompareFileTime" ], "Timesptamp": "00000002.965633", "FunctionName": "GetProcAddress", "ModuleName": "kernel32.dll", "Return": "0x74f21b25", "Status": 0 }
{ "Address": "0x419574", "Opcode": "ff95e0ba4000", "Opcodesize": 6, "Mnemonic": "call dword ptr [ebp + 0x40bae0]", "PID": 1712, "TID": 1768, "Arguments": [ "Arg1", "IN", "HMODULE", "0x18ff60", "0x74f10000", "Arg2", "IN", "LPCSTR", "0x18ff64", "MultiByteToWideChar" ], "Timesptamp": "00000002.996641", "FunctionName": "GetProcAddress", "ModuleName": "kernel32.dll", "Return": "0x74f2192e", "Status": 0 }
{ "Address": "0x419574", "Opcode": "ff95e0ba4000", "Opcodesize": 6, "Mnemonic": "call dword ptr [ebp + 0x40bae0]", "PID": 1712, "TID": 1768, "Arguments": [ "Arg1", "IN", "HMODULE", "0x18ff60", "0x74f10000", "Arg2", "IN", "LPCSTR", "0x18ff64", "WideCharToMultiByte" ], "Timesptamp": "00000003.016485", "FunctionName": "GetProcAddress", "ModuleName": "kernel32.dll", "Return": "0x74f2170d", "Status": 0 }
{ "Address": "0x419574", "Opcode": "ff95e0ba4000", "Opcodesize": 6, "Mnemonic": "call dword ptr [ebp + 0x40bae0]", "PID": 1712, "TID": 1768, "Arguments": [ "Arg1", "IN", "HMODULE", "0x18ff60", "0x74f10000", "Arg2", "IN", "LPCSTR", "0x18ff64", "CompareStringA" ], "Timesptamp": "00000003.047167", "FunctionName": "GetProcAddress", "ModuleName": "kernel32.dll", "Return": "0x74f23c5a", "Status": 0 }
{ "Address": "0x419574", "Opcode": "ff95e0ba4000", "Opcodesize": 6, "Mnemonic": "call dword ptr [ebp + 0x40bae0]", "PID": 1712, "TID": 1768, "Arguments": [ "Arg1", "IN", "HMODULE", "0x18ff60", "0x74f10000", "Arg2", "IN", "LPCSTR", "0x18ff64", "SetConsoleCtrlHandler" ], "Timesptamp": "00000003.075729", "FunctionName": "GetProcAddress", "ModuleName": "kernel32.dll", "Return": "0x74f28a09", "Status": 0 }
{ "Address": "0x419574", "Opcode": "ff95e0ba4000", "Opcodesize": 6, "Mnemonic": "call dword ptr [ebp + 0x40bae0]", "PID": 1712, "TID": 1768, "Arguments": [ "Arg1", "IN", "HMODULE", "0x18ff60", "0x74f10000", "Arg2", "IN", "LPCSTR", "0x18ff64", "FileTimeToDosDateTime" ], "Timesptamp": "00000003.099285", "FunctionName": "GetProcAddress", "ModuleName": "kernel32.dll", "Return": "0x74f3c86d", "Status": 0 }
{ "Address": "0x419574", "Opcode": "ff95e0ba4000", "Opcodesize": 6, "Mnemonic": "call dword ptr [ebp + 0x40bae0]", "PID": 1712, "TID": 1768, "Arguments": [ "Arg1", "IN", "HMODULE", "0x18ff60", "0x74f10000", "Arg2", "IN", "LPCSTR", "0x18ff64", "GetLastError" ], "Timesptamp": "00000003.124472", "FunctionName": "GetProcAddress", "ModuleName": "kernel32.dll", "Return": "0x74f211c0", "Status": 0 }
{ "Address": "0x419574", "Opcode": "ff95e0ba4000", "Opcodesize": 6, "Mnemonic": "call dword ptr [ebp + 0x40bae0]", "PID": 1712, "TID": 1768, "Arguments": [ "Arg1", "IN", "HMODULE", "0x18ff60", "0x74f10000", "Arg2", "IN", "LPCSTR", "0x18ff64", "SetFileApisToOEM" ], "Timesptamp": "00000003.153733", "FunctionName": "GetProcAddress", "ModuleName": "kernel32.dll", "Return": "0x74fa44f9", "Status": 0 }
{ "Address": "0x419574", "Opcode": "ff95e0ba4000", "Opcodesize": 6, "Mnemonic": "call dword ptr [ebp + 0x40bae0]", "PID": 1712, "TID": 1768, "Arguments": [ "Arg1", "IN", "HMODULE", "0x18ff60", "0x74f10000", "Arg2", "IN", "LPCSTR", "0x18ff64", "GetCommandLineW" ], "Timesptamp": "00000003.183939", "FunctionName": "GetProcAddress", "ModuleName": "kernel32.dll", "Return": "0x74f25223", "Status": 0 }
{ "Address": "0x419574", "Opcode": "ff95e0ba4000", "Opcodesize": 6, "Mnemonic": "call dword ptr [ebp + 0x40bae0]", "PID": 1712, "TID": 1768, "Arguments": [ "Arg1", "IN", "HMODULE", "0x18ff60", "0x74f10000", "Arg2", "IN", "LPCSTR", "0x18ff64", "AreFileApisANSI" ], "Timesptamp": "00000003.215268", "FunctionName": "GetProcAddress", "ModuleName": "kernel32.dll", "Return": "0x74fa40d1", "Status": 0 }
{ "Address": "0x419574", "Opcode": "ff95e0ba4000", "Opcodesize": 6, "Mnemonic": "call dword ptr [ebp + 0x40bae0]", "PID": 1712, "TID": 1768, "Arguments": [ "Arg1", "IN", "HMODULE", "0x18ff60", "0x74f10000", "Arg2", "IN", "LPCSTR", "0x18ff64", "FileTimeToLocalFileTime" ], "Timesptamp": "00000003.246131", "FunctionName": "GetProcAddress", "ModuleName": "kernel32.dll", "Return": "0x74f2e29e", "Status": 0 }
{ "Address": "0x419574", "Opcode": "ff95e0ba4000", "Opcodesize": 6, "Mnemonic": "call dword ptr [ebp + 0x40bae0]", "PID": 1712, "TID": 1768, "Arguments": [ "Arg1", "IN", "HMODULE", "0x18ff60", "0x74f10000", "Arg2", "IN", "LPCSTR", "0x18ff64", "FileTimeToSystemTime" ], "Timesptamp": "00000003.277437", "FunctionName": "GetProcAddress", "ModuleName": "kernel32.dll", "Return": "0x74f2542c", "Status": 0 }
{ "Address": "0x419574", "Opcode": "ff95e0ba4000", "Opcodesize": 6, "Mnemonic": "call dword ptr [ebp + 0x40bae0]", "PID": 1712, "TID": 1768, "Arguments": [ "Arg1", "IN", "HMODULE", "0x18ff60", "0x74f10000", "Arg2", "IN", "LPCSTR", "0x18ff64", "SearchPathW" ], "Timesptamp": "00000003.308707", "FunctionName": "GetProcAddress", "ModuleName": "kernel32.dll", "Return": "0x74f3cd70", "Status": 0 }
{ "Address": "0x419574", "Opcode": "ff95e0ba4000", "Opcodesize": 6, "Mnemonic": "call dword ptr [ebp + 0x40bae0]", "PID": 1712, "TID": 1768, "Arguments": [ "Arg1", "IN", "HMODULE", "0x18ff60", "0x74f10000", "Arg2", "IN", "LPCSTR", "0x18ff64", "SearchPathA" ], "Timesptamp": "00000003.340259", "FunctionName": "GetProcAddress", "ModuleName": "kernel32.dll", "Return": "0x74f3a15c", "Status": 0 }
{ "Address": "0x419574", "Opcode": "ff95e0ba4000", "Opcodesize": 6, "Mnemonic": "call dword ptr [ebp + 0x40bae0]", "PID": 1712, "TID": 1768, "Arguments": [ "Arg1", "IN", "HMODULE", "0x18ff60", "0x74f10000", "Arg2", "IN", "LPCSTR", "0x18ff64", "CompareStringW" ], "Timesptamp": "00000003.371327", "FunctionName": "GetProcAddress", "ModuleName": "kernel32.dll", "Return": "0x74f23bca", "Status": 0 }
{ "Address": "0x419241", "Opcode": "ff95d0d24000", "Opcodesize": 6, "Mnemonic": "call dword ptr [ebp + 0x40d2d0]", "PID": 1712, "TID": 1768, "Arguments": [ "Arg1", "IN", "LPCTSTR", "0x18ff68", "USER32.dll" ], "Timesptamp": "00000003.402499", "FunctionName": "GetModuleHandleA", "ModuleName": "kernel32.dll", "Return": "0x74d30000", "Status": 0 }
{ "Address": "0x419416", "Opcode": "ff95ecba4000", "Opcodesize": 6, "Mnemonic": "call dword ptr [ebp + 0x40baec]", "PID": 1712, "TID": 1768, "Arguments": [ "Arg1", "IN", "LPVOID", "0x18ff3c", "0x0", "Arg2", "IN", "SIZE_T", "0x18ff40", "0xc4", "Arg3", "IN", "DWORD", "0x18ff44", "0x1000", "Arg4", "IN", "DWORD", "0x18ff48", "0x4" ], "Timesptamp": "00000003.433345", "FunctionName": "VirtualAlloc", "ModuleName": "kernel32.dll", "Return": "0x2f0000", "Status": 0 }
{ "Address": "0x419574", "Opcode": "ff95e0ba4000", "Opcodesize": 6, "Mnemonic": "call dword ptr [ebp + 0x40bae0]", "PID": 1712, "TID": 1768, "Arguments": [ "Arg1", "IN", "HMODULE", "0x18ff60", "0x74d30000", "Arg2", "IN", "LPCSTR", "0x18ff64", "wsprintfA" ], "Timesptamp": "00000003.464746", "FunctionName": "GetProcAddress", "ModuleName": "kernel32.dll", "Return": "0x74d5ae5f", "Status": 0 }
{ "Address": "0x419574", "Opcode": "ff95e0ba4000", "Opcodesize": 6, "Mnemonic": "call dword ptr [ebp + 0x40bae0]", "PID": 1712, "TID": 1768, "Arguments": [ "Arg1", "IN", "HMODULE", "0x18ff60", "0x74d30000", "Arg2", "IN", "LPCSTR", "0x18ff64", "CharUpperA" ], "Timesptamp": "00000003.495745", "FunctionName": "GetProcAddress", "ModuleName": "kernel32.dll", "Return": "0x74d4fdca", "Status": 0 }
{ "Address": "0x419574", "Opcode": "ff95e0ba4000", "Opcodesize": 6, "Mnemonic": "call dword ptr [ebp + 0x40bae0]", "PID": 1712, "TID": 1768, "Arguments": [ "Arg1", "IN", "HMODULE", "0x18ff60", "0x74d30000", "Arg2", "IN", "LPCSTR", "0x18ff64", "CharNextA" ], "Timesptamp": "00000003.527148", "FunctionName": "GetProcAddress", "ModuleName": "kernel32.dll", "Return": "0x74d47a1b", "Status": 0 }
{ "Address": "0x419574", "Opcode": "ff95e0ba4000", "Opcodesize": 6, "Mnemonic": "call dword ptr [ebp + 0x40bae0]", "PID": 1712, "TID": 1768, "Arguments": [ "Arg1", "IN", "HMODULE", "0x18ff60", "0x74d30000", "Arg2", "IN", "LPCSTR", "0x18ff64", "CharUpperW" ], "Timesptamp": "00000003.558097", "FunctionName": "GetProcAddress", "ModuleName": "kernel32.dll", "Return": "0x74d4f350", "Status": 0 }
{ "Address": "0x419241", "Opcode": "ff95d0d24000", "Opcodesize": 6, "Mnemonic": "call dword ptr [ebp + 0x40d2d0]", "PID": 1712, "TID": 1768, "Arguments": [ "Arg1", "IN", "LPCTSTR", "0x18ff68", "ADVAPI32.dll" ], "Timesptamp": "00000003.589645", "FunctionName": "GetModuleHandleA", "ModuleName": "kernel32.dll", "Return": "0x74c00000", "Status": 0 }
{ "Address": "0x419574", "Opcode": "ff95e0ba4000", "Opcodesize": 6, "Mnemonic": "call dword ptr [ebp + 0x40bae0]", "PID": 1712, "TID": 1768, "Arguments": [ "Arg1", "IN", "HMODULE", "0x18ff60", "0x74c00000", "Arg2", "IN", "LPCSTR", "0x18ff64", "RegOpenKeyExA" ], "Timesptamp": "00000003.620851", "FunctionName": "GetProcAddress", "ModuleName": "kernel32.dll", "Return": "0x74c14907", "Status": 0 }
{ "Address": "0x419574", "Opcode": "ff95e0ba4000", "Opcodesize": 6, "Mnemonic": "call dword ptr [ebp + 0x40bae0]", "PID": 1712, "TID": 1768, "Arguments": [ "Arg1", "IN", "HMODULE", "0x18ff60", "0x74c00000", "Arg2", "IN", "LPCSTR", "0x18ff64", "RegCloseKey" ], "Timesptamp": "00000003.640753", "FunctionName": "GetProcAddress", "ModuleName": "kernel32.dll", "Return": "0x74c1469d", "Status": 0 }
{ "Address": "0x419574", "Opcode": "ff95e0ba4000", "Opcodesize": 6, "Mnemonic": "call dword ptr [ebp + 0x40bae0]", "PID": 1712, "TID": 1768, "Arguments": [ "Arg1", "IN", "HMODULE", "0x18ff60", "0x74c00000", "Arg2", "IN", "LPCSTR", "0x18ff64", "RegQueryValueExA" ], "Timesptamp": "00000003.668662", "FunctionName": "GetProcAddress", "ModuleName": "kernel32.dll", "Return": "0x74c148ef", "Status": 0 }
{ "Address": "0x419241", "Opcode": "ff95d0d24000", "Opcodesize": 6, "Mnemonic": "call dword ptr [ebp + 0x40d2d0]", "PID": 1712, "TID": 1768, "Arguments": [ "Arg1", "IN", "LPCTSTR", "0x18ff68", "ole32.dll" ], "Timesptamp": "00000003.698879", "FunctionName": "GetModuleHandleA", "ModuleName": "kernel32.dll", "Return": "0x0", "Status": 0 }
{ "Address": "0x419250", "Opcode": "ff95e4ba4000", "Opcodesize": 6, "Mnemonic": "call dword ptr [ebp + 0x40bae4]", "PID": 1712, "TID": 1768, "Arguments": [ "Arg1", "IN", "LPCTSTR", "0x18ff68", "ole32.dll" ], "Timesptamp": "00000003.723013", "FunctionName": "LoadLibraryA", "ModuleName": "kernel32.dll", "Return": "0x76660000", "Status": 0 }
{ "Address": "0x419574", "Opcode": "ff95e0ba4000", "Opcodesize": 6, "Mnemonic": "call dword ptr [ebp + 0x40bae0]", "PID": 1712, "TID": 1768, "Arguments": [ "Arg1", "IN", "HMODULE", "0x18ff60", "0x76660000", "Arg2", "IN", "LPCSTR", "0x18ff64", "CoInitialize" ], "Timesptamp": "00000003.765963", "FunctionName": "GetProcAddress", "ModuleName": "kernel32.dll", "Return": "0x7667b636", "Status": 0 }
{ "Address": "0x419574", "Opcode": "ff95e0ba4000", "Opcodesize": 6, "Mnemonic": "call dword ptr [ebp + 0x40bae0]", "PID": 1712, "TID": 1768, "Arguments": [ "Arg1", "IN", "HMODULE", "0x18ff60", "0x76660000", "Arg2", "IN", "LPCSTR", "0x18ff64", "CoUninitialize" ], "Timesptamp": "00000003.794252", "FunctionName": "GetProcAddress", "ModuleName": "kernel32.dll", "Return": "0x766a86d3", "Status": 0 }
{ "Address": "0x419241", "Opcode": "ff95d0d24000", "Opcodesize": 6, "Mnemonic": "call dword ptr [ebp + 0x40d2d0]", "PID": 1712, "TID": 1768, "Arguments": [ "Arg1", "IN", "LPCTSTR", "0x18ff68", "OLEAUT32.dll" ], "Timesptamp": "00000003.825882", "FunctionName": "GetModuleHandleA", "ModuleName": "kernel32.dll", "Return": "0x0", "Status": 0 }
{ "Address": "0x419250", "Opcode": "ff95e4ba4000", "Opcodesize": 6, "Mnemonic": "call dword ptr [ebp + 0x40bae4]", "PID": 1712, "TID": 1768, "Arguments": [ "Arg1", "IN", "LPCTSTR", "0x18ff68", "OLEAUT32.dll" ], "Timesptamp": "00000003.856006", "FunctionName": "LoadLibraryA", "ModuleName": "kernel32.dll", "Return": "0x74ca0000", "Status": 0 }
{ "Address": "0x419574", "Opcode": "ff95e0ba4000", "Opcodesize": 6, "Mnemonic": "call dword ptr [ebp + 0x40bae0]", "PID": 1712, "TID": 1768, "Arguments": [ "Arg1", "IN", "HMODULE", "0x18ff60", "0x74ca0000", "Arg2", "IN", "USHORT", "0x18ff64", "0xa" ], "Timesptamp": "00000003.905265", "FunctionName": "GetProcAddressOrdinal", "ModuleName": "kernel32.dll", "Return": "0x74ca48f1", "Status": 0 }
{ "Address": "0x419574", "Opcode": "ff95e0ba4000", "Opcodesize": 6, "Mnemonic": "call dword ptr [ebp + 0x40bae0]", "PID": 1712, "TID": 1768, "Arguments": [ "Arg1", "IN", "HMODULE", "0x18ff60", "0x74ca0000", "Arg2", "IN", "USHORT", "0x18ff64", "0x9" ], "Timesptamp": "00000003.934052", "FunctionName": "GetProcAddressOrdinal", "ModuleName": "kernel32.dll", "Return": "0x74ca3eae", "Status": 0 }
{ "Address": "0x419574", "Opcode": "ff95e0ba4000", "Opcodesize": 6, "Mnemonic": "call dword ptr [ebp + 0x40bae0]", "PID": 1712, "TID": 1768, "Arguments": [ "Arg1", "IN", "HMODULE", "0x18ff60", "0x74ca0000", "Arg2", "IN", "USHORT", "0x18ff64", "0x95" ], "Timesptamp": "00000003.963367", "FunctionName": "GetProcAddressOrdinal", "ModuleName": "kernel32.dll", "Return": "0x74ca46a5", "Status": 0 }
{ "Address": "0x419574", "Opcode": "ff95e0ba4000", "Opcodesize": 6, "Mnemonic": "call dword ptr [ebp + 0x40bae0]", "PID": 1712, "TID": 1768, "Arguments": [ "Arg1", "IN", "HMODULE", "0x18ff60", "0x74ca0000", "Arg2", "IN", "USHORT", "0x18ff64", "0x96" ], "Timesptamp": "00000003.995249", "FunctionName": "GetProcAddressOrdinal", "ModuleName": "kernel32.dll", "Return": "0x74ca4731", "Status": 0 }
{ "Address": "0x419574", "Opcode": "ff95e0ba4000", "Opcodesize": 6, "Mnemonic": "call dword ptr [ebp + 0x40bae0]", "PID": 1712, "TID": 1768, "Arguments": [ "Arg1", "IN", "HMODULE", "0x18ff60", "0x74ca0000", "Arg2", "IN", "USHORT", "0x18ff64", "0x2" ], "Timesptamp": "00000004.030395", "FunctionName": "GetProcAddressOrdinal", "ModuleName": "kernel32.dll", "Return": "0x74ca4642", "Status": 0 }
{ "Address": "0x419574", "Opcode": "ff95e0ba4000", "Opcodesize": 6, "Mnemonic": "call dword ptr [ebp + 0x40bae0]", "PID": 1712, "TID": 1768, "Arguments": [ "Arg1", "IN", "HMODULE", "0x18ff60", "0x74ca0000", "Arg2", "IN", "USHORT", "0x18ff64", "0x6" ], "Timesptamp": "00000004.059742", "FunctionName": "GetProcAddressOrdinal", "ModuleName": "kernel32.dll", "Return": "0x74ca3e59", "Status": 0 }
{ "Address": "0x419241", "Opcode": "ff95d0d24000", "Opcodesize": 6, "Mnemonic": "call dword ptr [ebp + 0x40d2d0]", "PID": 1712, "TID": 1768, "Arguments": [ "Arg1", "IN", "LPCTSTR", "0x18ff68", "MSVCRT.dll" ], "Timesptamp": "00000004.089794", "FunctionName": "GetModuleHandleA", "ModuleName": "kernel32.dll", "Return": "0x76190000", "Status": 0 }
{ "Address": "0x419574", "Opcode": "ff95e0ba4000", "Opcodesize": 6, "Mnemonic": "call dword ptr [ebp + 0x40bae0]", "PID": 1712, "TID": 1768, "Arguments": [ "Arg1", "IN", "HMODULE", "0x18ff60", "0x76190000", "Arg2", "IN", "LPCSTR", "0x18ff64", "wcslen" ], "Timesptamp": "00000004.114160", "FunctionName": "GetProcAddress", "ModuleName": "kernel32.dll", "Return": "0x761ad335", "Status": 0 }
{ "Address": "0x419574", "Opcode": "ff95e0ba4000", "Opcodesize": 6, "Mnemonic": "call dword ptr [ebp + 0x40bae0]", "PID": 1712, "TID": 1768, "Arguments": [ "Arg1", "IN", "HMODULE", "0x18ff60", "0x76190000", "Arg2", "IN", "LPCSTR", "0x18ff64", "memmove" ], "Timesptamp": "00000004.139160", "FunctionName": "GetProcAddress", "ModuleName": "kernel32.dll", "Return": "0x76199e5a", "Status": 0 }
{ "Address": "0x419574", "Opcode": "ff95e0ba4000", "Opcodesize": 6, "Mnemonic": "call dword ptr [ebp + 0x40bae0]", "PID": 1712, "TID": 1768, "Arguments": [ "Arg1", "IN", "HMODULE", "0x18ff60", "0x76190000", "Arg2", "IN", "LPCSTR", "0x18ff64", "memcpy" ], "Timesptamp": "00000004.168568", "FunctionName": "GetProcAddress", "ModuleName": "kernel32.dll", "Return": "0x76199910", "Status": 0 }
{ "Address": "0x419574", "Opcode": "ff95e0ba4000", "Opcodesize": 6, "Mnemonic": "call dword ptr [ebp + 0x40bae0]", "PID": 1712, "TID": 1768, "Arguments": [ "Arg1", "IN", "HMODULE", "0x18ff60", "0x76190000", "Arg2", "IN", "LPCSTR", "0x18ff64", "__set_app_type" ], "Timesptamp": "00000004.198793", "FunctionName": "GetProcAddress", "ModuleName": "kernel32.dll", "Return": "0x761a2804", "Status": 0 }
{ "Address": "0x419574", "Opcode": "ff95e0ba4000", "Opcodesize": 6, "Mnemonic": "call dword ptr [ebp + 0x40bae0]", "PID": 1712, "TID": 1768, "Arguments": [ "Arg1", "IN", "HMODULE", "0x18ff60", "0x76190000", "Arg2", "IN", "LPCSTR", "0x18ff64", "__p__fmode" ], "Timesptamp": "00000004.230179", "FunctionName": "GetProcAddress", "ModuleName": "kernel32.dll", "Return": "0x761a27ce", "Status": 0 }
{ "Address": "0x419574", "Opcode": "ff95e0ba4000", "Opcodesize": 6, "Mnemonic": "call dword ptr [ebp + 0x40bae0]", "PID": 1712, "TID": 1768, "Arguments": [ "Arg1", "IN", "HMODULE", "0x18ff60", "0x76190000", "Arg2", "IN", "LPCSTR", "0x18ff64", "__p__commode" ], "Timesptamp": "00000004.259466", "FunctionName": "GetProcAddress", "ModuleName": "kernel32.dll", "Return": "0x761a27c3", "Status": 0 }
{ "Address": "0x419574", "Opcode": "ff95e0ba4000", "Opcodesize": 6, "Mnemonic": "call dword ptr [ebp + 0x40bae0]", "PID": 1712, "TID": 1768, "Arguments": [ "Arg1", "IN", "HMODULE", "0x18ff60", "0x76190000", "Arg2", "IN", "LPCSTR", "0x18ff64", "_adjust_fdiv" ], "Timesptamp": "00000004.281054", "FunctionName": "GetProcAddress", "ModuleName": "kernel32.dll", "Return": "0x762332ec", "Status": 0 }
{ "Address": "0x419574", "Opcode": "ff95e0ba4000", "Opcodesize": 6, "Mnemonic": "call dword ptr [ebp + 0x40bae0]", "PID": 1712, "TID": 1768, "Arguments": [ "Arg1", "IN", "HMODULE", "0x18ff60", "0x76190000", "Arg2", "IN", "LPCSTR", "0x18ff64", "__setusermatherr" ], "Timesptamp": "00000004.306303", "FunctionName": "GetProcAddress", "ModuleName": "kernel32.dll", "Return": "0x762277ad", "Status": 0 }
{ "Address": "0x419574", "Opcode": "ff95e0ba4000", "Opcodesize": 6, "Mnemonic": "call dword ptr [ebp + 0x40bae0]", "PID": 1712, "TID": 1768, "Arguments": [ "Arg1", "IN", "HMODULE", "0x18ff60", "0x76190000", "Arg2", "IN", "LPCSTR", "0x18ff64", "_fileno" ], "Timesptamp": "00000004.323592", "FunctionName": "GetProcAddress", "ModuleName": "kernel32.dll", "Return": "0x7619ac15", "Status": 0 }
{ "Address": "0x419574", "Opcode": "ff95e0ba4000", "Opcodesize": 6, "Mnemonic": "call dword ptr [ebp + 0x40bae0]", "PID": 1712, "TID": 1768, "Arguments": [ "Arg1", "IN", "HMODULE", "0x18ff60", "0x76190000", "Arg2", "IN", "LPCSTR", "0x18ff64", "_isatty" ], "Timesptamp": "00000004.342769", "FunctionName": "GetProcAddress", "ModuleName": "kernel32.dll", "Return": "0x7619f383", "Status": 0 }
{ "Address": "0x419574", "Opcode": "ff95e0ba4000", "Opcodesize": 6, "Mnemonic": "call dword ptr [ebp + 0x40bae0]", "PID": 1712, "TID": 1768, "Arguments": [ "Arg1", "IN", "HMODULE", "0x18ff60", "0x76190000", "Arg2", "IN", "LPCSTR", "0x18ff64", "_controlfp" ], "Timesptamp": "00000004.366317", "FunctionName": "GetProcAddress", "ModuleName": "kernel32.dll", "Return": "0x7619e1e1", "Status": 0 }
{ "Address": "0x419574", "Opcode": "ff95e0ba4000", "Opcodesize": 6, "Mnemonic": "call dword ptr [ebp + 0x40bae0]", "PID": 1712, "TID": 1768, "Arguments": [ "Arg1", "IN", "HMODULE", "0x18ff60", "0x76190000", "Arg2", "IN", "LPCSTR", "0x18ff64", "malloc" ], "Timesptamp": "00000004.384692", "FunctionName": "GetProcAddress", "ModuleName": "kernel32.dll", "Return": "0x76199cee", "Status": 0 }
{ "Address": "0x419574", "Opcode": "ff95e0ba4000", "Opcodesize": 6, "Mnemonic": "call dword ptr [ebp + 0x40bae0]", "PID": 1712, "TID": 1768, "Arguments": [ "Arg1", "IN", "HMODULE", "0x18ff60", "0x76190000", "Arg2", "IN", "LPCSTR", "0x18ff64", "__p___initenv" ], "Timesptamp": "00000004.404186", "FunctionName": "GetProcAddress", "ModuleName": "kernel32.dll", "Return": "0x761a0251", "Status": 0 }
{ "Address": "0x419574", "Opcode": "ff95e0ba4000", "Opcodesize": 6, "Mnemonic": "call dword ptr [ebp + 0x40bae0]", "PID": 1712, "TID": 1768, "Arguments": [ "Arg1", "IN", "HMODULE", "0x18ff60", "0x76190000", "Arg2", "IN", "LPCSTR", "0x18ff64", "exit" ], "Timesptamp": "00000004.427994", "FunctionName": "GetProcAddress", "ModuleName": "kernel32.dll", "Return": "0x761a36aa", "Status": 0 }
{ "Address": "0x419574", "Opcode": "ff95e0ba4000", "Opcodesize": 6, "Mnemonic": "call dword ptr [ebp + 0x40bae0]", "PID": 1712, "TID": 1768, "Arguments": [ "Arg1", "IN", "HMODULE", "0x18ff60", "0x76190000", "Arg2", "IN", "LPCSTR", "0x18ff64", "_XcptFilter" ], "Timesptamp": "00000004.446815", "FunctionName": "GetProcAddress", "ModuleName": "kernel32.dll", "Return": "0x761bdc75", "Status": 0 }
{ "Address": "0x419574", "Opcode": "ff95e0ba4000", "Opcodesize": 6, "Mnemonic": "call dword ptr [ebp + 0x40bae0]", "PID": 1712, "TID": 1768, "Arguments": [ "Arg1", "IN", "HMODULE", "0x18ff60", "0x76190000", "Arg2", "IN", "LPCSTR", "0x18ff64", "_exit" ], "Timesptamp": "00000004.466489", "FunctionName": "GetProcAddress", "ModuleName": "kernel32.dll", "Return": "0x761fb2c0", "Status": 0 }
{ "Address": "0x419574", "Opcode": "ff95e0ba4000", "Opcodesize": 6, "Mnemonic": "call dword ptr [ebp + 0x40bae0]", "PID": 1712, "TID": 1768, "Arguments": [ "Arg1", "IN", "HMODULE", "0x18ff60", "0x76190000", "Arg2", "IN", "LPCSTR", "0x18ff64", "?terminate@@YAXXZ" ], "Timesptamp": "00000004.490226", "FunctionName": "GetProcAddress", "ModuleName": "kernel32.dll", "Return": "0x761e61cf", "Status": 0 }
{ "Address": "0x419574", "Opcode": "ff95e0ba4000", "Opcodesize": 6, "Mnemonic": "call dword ptr [ebp + 0x40bae0]", "PID": 1712, "TID": 1768, "Arguments": [ "Arg1", "IN", "HMODULE", "0x18ff60", "0x76190000", "Arg2", "IN", "LPCSTR", "0x18ff64", "_except_handler3" ], "Timesptamp": "00000004.509240", "FunctionName": "GetProcAddress", "ModuleName": "kernel32.dll", "Return": "0x761bd770", "Status": 0 }
{ "Address": "0x419574", "Opcode": "ff95e0ba4000", "Opcodesize": 6, "Mnemonic": "call dword ptr [ebp + 0x40bae0]", "PID": 1712, "TID": 1768, "Arguments": [ "Arg1", "IN", "HMODULE", "0x18ff60", "0x76190000", "Arg2", "IN", "LPCSTR", "0x18ff64", "_onexit" ], "Timesptamp": "00000004.528742", "FunctionName": "GetProcAddress", "ModuleName": "kernel32.dll", "Return": "0x761a112d", "Status": 0 }
{ "Address": "0x419574", "Opcode": "ff95e0ba4000", "Opcodesize": 6, "Mnemonic": "call dword ptr [ebp + 0x40bae0]", "PID": 1712, "TID": 1768, "Arguments": [ "Arg1", "IN", "HMODULE", "0x18ff60", "0x76190000", "Arg2", "IN", "LPCSTR", "0x18ff64", "__dllonexit" ], "Timesptamp": "00000004.552462", "FunctionName": "GetProcAddress", "ModuleName": "kernel32.dll", "Return": "0x7619f509", "Status": 0 }
{ "Address": "0x419574", "Opcode": "ff95e0ba4000", "Opcodesize": 6, "Mnemonic": "call dword ptr [ebp + 0x40bae0]", "PID": 1712, "TID": 1768, "Arguments": [ "Arg1", "IN", "HMODULE", "0x18ff60", "0x76190000", "Arg2", "IN", "LPCSTR", "0x18ff64", "??1type_info@@UAE@XZ" ], "Timesptamp": "00000004.571566", "FunctionName": "GetProcAddress", "ModuleName": "kernel32.dll", "Return": "0x761e92b3", "Status": 0 }
{ "Address": "0x419574", "Opcode": "ff95e0ba4000", "Opcodesize": 6, "Mnemonic": "call dword ptr [ebp + 0x40bae0]", "PID": 1712, "TID": 1768, "Arguments": [ "Arg1", "IN", "HMODULE", "0x18ff60", "0x76190000", "Arg2", "IN", "LPCSTR", "0x18ff64", "_CxxThrowException" ], "Timesptamp": "00000004.591310", "FunctionName": "GetProcAddress", "ModuleName": "kernel32.dll", "Return": "0x761b3557", "Status": 0 }
{ "Address": "0x419574", "Opcode": "ff95e0ba4000", "Opcodesize": 6, "Mnemonic": "call dword ptr [ebp + 0x40bae0]", "PID": 1712, "TID": 1768, "Arguments": [ "Arg1", "IN", "HMODULE", "0x18ff60", "0x76190000", "Arg2", "IN", "LPCSTR", "0x18ff64", "__CxxFrameHandler" ], "Timesptamp": "00000004.615021", "FunctionName": "GetProcAddress", "ModuleName": "kernel32.dll", "Return": "0x761b3495", "Status": 0 }
{ "Address": "0x419574", "Opcode": "ff95e0ba4000", "Opcodesize": 6, "Mnemonic": "call dword ptr [ebp + 0x40bae0]", "PID": 1712, "TID": 1768, "Arguments": [ "Arg1", "IN", "HMODULE", "0x18ff60", "0x76190000", "Arg2", "IN", "LPCSTR", "0x18ff64", "memcmp" ], "Timesptamp": "00000004.633947", "FunctionName": "GetProcAddress", "ModuleName": "kernel32.dll", "Return": "0x761a7975", "Status": 0 }
{ "Address": "0x419574", "Opcode": "ff95e0ba4000", "Opcodesize": 6, "Mnemonic": "call dword ptr [ebp + 0x40bae0]", "PID": 1712, "TID": 1768, "Arguments": [ "Arg1", "IN", "HMODULE", "0x18ff60", "0x76190000", "Arg2", "IN", "LPCSTR", "0x18ff64", "_iob" ], "Timesptamp": "00000004.653612", "FunctionName": "GetProcAddress", "ModuleName": "kernel32.dll", "Return": "0x76232900", "Status": 0 }
{ "Address": "0x419574", "Opcode": "ff95e0ba4000", "Opcodesize": 6, "Mnemonic": "call dword ptr [ebp + 0x40bae0]", "PID": 1712, "TID": 1768, "Arguments": [ "Arg1", "IN", "HMODULE", "0x18ff60", "0x76190000", "Arg2", "IN", "LPCSTR", "0x18ff64", "wcstoul" ], "Timesptamp": "00000004.677395", "FunctionName": "GetProcAddress", "ModuleName": "kernel32.dll", "Return": "0x7619b319", "Status": 0 }
{ "Address": "0x419574", "Opcode": "ff95e0ba4000", "Opcodesize": 6, "Mnemonic": "call dword ptr [ebp + 0x40bae0]", "PID": 1712, "TID": 1768, "Arguments": [ "Arg1", "IN", "HMODULE", "0x18ff60", "0x76190000", "Arg2", "IN", "LPCSTR", "0x18ff64", "_initterm" ], "Timesptamp": "00000004.696465", "FunctionName": "GetProcAddress", "ModuleName": "kernel32.dll", "Return": "0x7619c151", "Status": 0 }
{ "Address": "0x419574", "Opcode": "ff95e0ba4000", "Opcodesize": 6, "Mnemonic": "call dword ptr [ebp + 0x40bae0]", "PID": 1712, "TID": 1768, "Arguments": [ "Arg1", "IN", "HMODULE", "0x18ff60", "0x76190000", "Arg2", "IN", "LPCSTR", "0x18ff64", "__getmainargs" ], "Timesptamp": "00000004.716075", "FunctionName": "GetProcAddress", "ModuleName": "kernel32.dll", "Return": "0x761a2bc0", "Status": 0 }
{ "Address": "0x419574", "Opcode": "ff95e0ba4000", "Opcodesize": 6, "Mnemonic": "call dword ptr [ebp + 0x40bae0]", "PID": 1712, "TID": 1768, "Arguments": [ "Arg1", "IN", "HMODULE", "0x18ff60", "0x76190000", "Arg2", "IN", "LPCSTR", "0x18ff64", "qsort" ], "Timesptamp": "00000004.739707", "FunctionName": "GetProcAddress", "ModuleName": "kernel32.dll", "Return": "0x7619d3e6", "Status": 0 }
{ "Address": "0x419574", "Opcode": "ff95e0ba4000", "Opcodesize": 6, "Mnemonic": "call dword ptr [ebp + 0x40bae0]", "PID": 1712, "TID": 1768, "Arguments": [ "Arg1", "IN", "HMODULE", "0x18ff60", "0x76190000", "Arg2", "IN", "LPCSTR", "0x18ff64", "free" ], "Timesptamp": "00000004.758776", "FunctionName": "GetProcAddress", "ModuleName": "kernel32.dll", "Return": "0x76199894", "Status": 0 }
{ "Address": "0x419574", "Opcode": "ff95e0ba4000", "Opcodesize": 6, "Mnemonic": "call dword ptr [ebp + 0x40bae0]", "PID": 1712, "TID": 1768, "Arguments": [ "Arg1", "IN", "HMODULE", "0x18ff60", "0x76190000", "Arg2", "IN", "LPCSTR", "0x18ff64", "fopen" ], "Timesptamp": "00000004.778365", "FunctionName": "GetProcAddress", "ModuleName": "kernel32.dll", "Return": "0x761ab2c4", "Status": 0 }
{ "Address": "0x419574", "Opcode": "ff95e0ba4000", "Opcodesize": 6, "Mnemonic": "call dword ptr [ebp + 0x40bae0]", "PID": 1712, "TID": 1768, "Arguments": [ "Arg1", "IN", "HMODULE", "0x18ff60", "0x76190000", "Arg2", "IN", "LPCSTR", "0x18ff64", "fclose" ], "Timesptamp": "00000004.800502", "FunctionName": "GetProcAddress", "ModuleName": "kernel32.dll", "Return": "0x761a3d79", "Status": 0 }
{ "Address": "0x419574", "Opcode": "ff95e0ba4000", "Opcodesize": 6, "Mnemonic": "call dword ptr [ebp + 0x40bae0]", "PID": 1712, "TID": 1768, "Arguments": [ "Arg1", "IN", "HMODULE", "0x18ff60", "0x76190000", "Arg2", "IN", "LPCSTR", "0x18ff64", "getc" ], "Timesptamp": "00000004.821106", "FunctionName": "GetProcAddress", "ModuleName": "kernel32.dll", "Return": "0x761a9950", "Status": 0 }
{ "Address": "0x419574", "Opcode": "ff95e0ba4000", "Opcodesize": 6, "Mnemonic": "call dword ptr [ebp + 0x40bae0]", "PID": 1712, "TID": 1768, "Arguments": [ "Arg1", "IN", "HMODULE", "0x18ff60", "0x76190000", "Arg2", "IN", "LPCSTR", "0x18ff64", "fputs" ], "Timesptamp": "00000004.837885", "FunctionName": "GetProcAddress", "ModuleName": "kernel32.dll", "Return": "0x761b6c38", "Status": 0 }
{ "Address": "0x419574", "Opcode": "ff95e0ba4000", "Opcodesize": 6, "Mnemonic": "call dword ptr [ebp + 0x40bae0]", "PID": 1712, "TID": 1768, "Arguments": [ "Arg1", "IN", "HMODULE", "0x18ff60", "0x76190000", "Arg2", "IN", "LPCSTR", "0x18ff64", "fputc" ], "Timesptamp": "00000004.857001", "FunctionName": "GetProcAddress", "ModuleName": "kernel32.dll", "Return": "0x762087c3", "Status": 0 }
{ "Address": "0x419087", "Opcode": "ff95ecba4000", "Opcodesize": 6, "Mnemonic": "call dword ptr [ebp + 0x40baec]", "PID": 1712, "TID": 1768, "Arguments": [ "Arg1", "IN", "LPVOID", "0x18ff30", "0x0", "Arg2", "IN", "SIZE_T", "0x18ff34", "0x17", "Arg3", "IN", "DWORD", "0x18ff38", "0x1000", "Arg4", "IN", "DWORD", "0x18ff3c", "0x4" ], "Timesptamp": "00000004.880538", "FunctionName": "VirtualAlloc", "ModuleName": "kernel32.dll", "Return": "0x300000", "Status": 0 }
{ "Address": "0x419159", "Opcode": "ff95f0ba4000", "Opcodesize": 6, "Mnemonic": "call dword ptr [ebp + 0x40baf0]", "PID": 1712, "TID": 1768, "Arguments": [ "Arg1", "IN", "LPVOID", "0x18ff34", "0x300000", "Arg2", "IN", "SIZE_T", "0x18ff38", "0x17", "Arg3", "IN", "DWORD", "0x18ff3c", "0x4000" ], "Timesptamp": "00000004.899621", "FunctionName": "VirtualFree", "ModuleName": "kernel32.dll", "Return": "TRUE", "Status": 0 }
{ "Address": "0x41968e", "Opcode": "ff95f8ba4000", "Opcodesize": 6, "Mnemonic": "call dword ptr [ebp + 0x40baf8]", "PID": 1712, "TID": 1768, "Arguments": [ ], "Timesptamp": "00000004.919173", "FunctionName": "GetCurrentProcessId", "ModuleName": "kernel32.dll", "Return": "0x6b0", "Status": 0 }
{ "Address": "0x41969e", "Opcode": "ff95fcba4000", "Opcodesize": 6, "Mnemonic": "call dword ptr [ebp + 0x40bafc]", "PID": 1712, "TID": 1768, "Arguments": [ "Arg1", "IN", "DWORD", "0x18ff60", "0x1f0fff", "Arg2", "IN", "BOOL", "0x18ff64", "FALSE", "Arg3", "IN", "DWORD", "0x18ff68", "0x6b0" ], "Timesptamp": "00000004.933002", "FunctionName": "OpenProcess", "ModuleName": "kernel32.dll", "Return": "0x84", "Status": 0 }
{ "Address": "0x4196b9", "Opcode": "ff9500bb4000", "Opcodesize": 6, "Mnemonic": "call dword ptr [ebp + 0x40bb00]", "PID": 1712, "TID": 1768, "Arguments": [ "Arg1", "IN", "HANDLE", "0x18ff54", "0x300000", "Arg2", "IN", "LPVOID", "0x18ff58", "0x400000", "Arg3", "IN", "SIZE_T", "0x18ff5c", "0x1000", "Arg4", "IN", "DWORD", "0x18ff60", "0x4", "Arg5", "OUT", "PDWORD", "0x18ff64", "0x18ff68" ], "Timesptamp": "00000004.947698", "FunctionName": "VirtualProtectEx", "ModuleName": "kernel32.dll", "Return": "FALSE", "Output1": [ "0x18ff68", "0x0" ], "Status": 0 }
{ "Address": "0x40ec06", "Opcode": "ff1510114100", "Opcodesize": 6, "Mnemonic": "call dword ptr [0x411110]", "PID": 1712, "TID": 1768, "Arguments": [ ], "Timesptamp": "00000005.044753", "FunctionName": "__p__fmode", "ModuleName": "msvcrt.dll", "Return": "0x762331f4", "Status": 0 }
{ "Address": "0x40ec14", "Opcode": "ff1514114100", "Opcodesize": 6, "Mnemonic": "call dword ptr [0x411114]", "PID": 1712, "TID": 1768, "Arguments": [ ], "Timesptamp": "00000005.059492", "FunctionName": "__p__commode", "ModuleName": "msvcrt.dll", "Return": "0x762331fc", "Status": 0 }
{ "Address": "0x40ed04", "Opcode": "e807000000", "Opcodesize": 5, "Mnemonic": "call 0x40ed10", "PID": 1712, "TID": 1768, "Functionname": "_controlfp", "Dllname": "msvcrt.dll", "Status": 1 }
{ "Address": "0x40ec57", "Opcode": "e898000000", "Opcodesize": 5, "Mnemonic": "call 0x40ecf4", "PID": 1712, "TID": 1768, "Functionname": "_initterm", "Dllname": "msvcrt.dll", "Status": 1 }
{ "Address": "0x40ec7a", "Opcode": "ff156c114100", "Opcodesize": 6, "Mnemonic": "call dword ptr [0x41116c]", "PID": 1712, "TID": 1768, "Functionname": "__getmainargs", "Dllname": "msvcrt.dll", "Status": 1 }
{ "Address": "0x40ec8a", "Opcode": "e865000000", "Opcodesize": 5, "Mnemonic": "call 0x40ecf4", "PID": 1712, "TID": 1768, "Functionname": "_initterm", "Dllname": "msvcrt.dll", "Status": 1 }
{ "Address": "0x40e8f3", "Opcode": "ff1548114100", "Opcodesize": 6, "Mnemonic": "call dword ptr [0x411148]", "PID": 1712, "TID": 1768, "Functionname": "_onexit", "Dllname": "msvcrt.dll", "Status": 1 }
{ "Address": "0x40b5e0", "Opcode": "ff152c114100", "Opcodesize": 6, "Mnemonic": "call dword ptr [0x41112c]", "PID": 1712, "TID": 1768, "Arguments": [ "Arg1", "IN", "SIZE_T", "0x18fed4", "0xa" ], "Timesptamp": "00000005.169207", "FunctionName": "malloc", "ModuleName": "msvcrt.dll", "Return": "0x3b12c8", "Status": 0 }
{ "Address": "0x40e8f3", "Opcode": "ff1548114100", "Opcodesize": 6, "Mnemonic": "call dword ptr [0x411148]", "PID": 1712, "TID": 1768, "Functionname": "_onexit", "Dllname": "msvcrt.dll", "Status": 1 }
{ "Address": "0x40b5e0", "Opcode": "ff152c114100", "Opcodesize": 6, "Mnemonic": "call dword ptr [0x41112c]", "PID": 1712, "TID": 1768, "Arguments": [ "Arg1", "IN", "SIZE_T", "0x18fedc", "0xb" ], "Timesptamp": "00000005.216826", "FunctionName": "malloc", "ModuleName": "msvcrt.dll", "Return": "0x3b12e0", "Status": 0 }
{ "Address": "0x40e8f3", "Opcode": "ff1548114100", "Opcodesize": 6, "Mnemonic": "call dword ptr [0x411148]", "PID": 1712, "TID": 1768, "Functionname": "_onexit", "Dllname": "msvcrt.dll", "Status": 1 }
{ "Address": "0x40b5e0", "Opcode": "ff152c114100", "Opcodesize": 6, "Mnemonic": "call dword ptr [0x41112c]", "PID": 1712, "TID": 1768, "Arguments": [ "Arg1", "IN", "SIZE_T", "0x18fedc", "0x8" ], "Timesptamp": "00000005.264271", "FunctionName": "malloc", "ModuleName": "msvcrt.dll", "Return": "0x3b12f8", "Status": 0 }
{ "Address": "0x40e8f3", "Opcode": "ff1548114100", "Opcodesize": 6, "Mnemonic": "call dword ptr [0x411148]", "PID": 1712, "TID": 1768, "Functionname": "_onexit", "Dllname": "msvcrt.dll", "Status": 1 }
{ "Address": "0x40b5e0", "Opcode": "ff152c114100", "Opcodesize": 6, "Mnemonic": "call dword ptr [0x41112c]", "PID": 1712, "TID": 1768, "Arguments": [ "Arg1", "IN", "SIZE_T", "0x18fedc", "0x1" ], "Timesptamp": "00000005.309372", "FunctionName": "malloc", "ModuleName": "msvcrt.dll", "Return": "0x3b1308", "Status": 0 }
{ "Address": "0x40e8f3", "Opcode": "ff1548114100", "Opcodesize": 6, "Mnemonic": "call dword ptr [0x411148]", "PID": 1712, "TID": 1768, "Functionname": "_onexit", "Dllname": "msvcrt.dll", "Status": 1 }
{ "Address": "0x40e8f3", "Opcode": "ff1548114100", "Opcodesize": 6, "Mnemonic": "call dword ptr [0x411148]", "PID": 1712, "TID": 1768, "Functionname": "_onexit", "Dllname": "msvcrt.dll", "Status": 1 }
{ "Address": "0x40e8f3", "Opcode": "ff1548114100", "Opcodesize": 6, "Mnemonic": "call dword ptr [0x411148]", "PID": 1712, "TID": 1768, "Functionname": "_onexit", "Dllname": "msvcrt.dll", "Status": 1 }
{ "Address": "0x40e8f3", "Opcode": "ff1548114100", "Opcodesize": 6, "Mnemonic": "call dword ptr [0x411148]", "PID": 1712, "TID": 1768, "Functionname": "_onexit", "Dllname": "msvcrt.dll", "Status": 1 }
{ "Address": "0x40b5e0", "Opcode": "ff152c114100", "Opcodesize": 6, "Mnemonic": "call dword ptr [0x41112c]", "PID": 1712, "TID": 1768, "Arguments": [ "Arg1", "IN", "SIZE_T", "0x18fed4", "0x2" ], "Timesptamp": "00000005.450717", "FunctionName": "malloc", "ModuleName": "msvcrt.dll", "Return": "0x3b1318", "Status": 0 }
{ "Address": "0x40e8f3", "Opcode": "ff1548114100", "Opcodesize": 6, "Mnemonic": "call dword ptr [0x411148]", "PID": 1712, "TID": 1768, "Functionname": "_onexit", "Dllname": "msvcrt.dll", "Status": 1 }
{ "Address": "0x40b5e0", "Opcode": "ff152c114100", "Opcodesize": 6, "Mnemonic": "call dword ptr [0x41112c]", "PID": 1712, "TID": 1768, "Arguments": [ "Arg1", "IN", "SIZE_T", "0x18fed4", "0x6" ], "Timesptamp": "00000005.497175", "FunctionName": "malloc", "ModuleName": "msvcrt.dll", "Return": "0x3b1328", "Status": 0 }
{ "Address": "0x40e8f3", "Opcode": "ff1548114100", "Opcodesize": 6, "Mnemonic": "call dword ptr [0x411148]", "PID": 1712, "TID": 1768, "Functionname": "_onexit", "Dllname": "msvcrt.dll", "Status": 1 }
{ "Address": "0x40b5e0", "Opcode": "ff152c114100", "Opcodesize": 6, "Mnemonic": "call dword ptr [0x41112c]", "PID": 1712, "TID": 1768, "Arguments": [ "Arg1", "IN", "SIZE_T", "0x18fed4", "0x4e" ], "Timesptamp": "00000005.544536", "FunctionName": "malloc", "ModuleName": "msvcrt.dll", "Return": "0x3b22f8", "Status": 0 }
{ "Address": "0x40e8f3", "Opcode": "ff1548114100", "Opcodesize": 6, "Mnemonic": "call dword ptr [0x411148]", "PID": 1712, "TID": 1768, "Functionname": "_onexit", "Dllname": "msvcrt.dll", "Status": 1 }
{ "Address": "0x40b5e0", "Opcode": "ff152c114100", "Opcodesize": 6, "Mnemonic": "call dword ptr [0x41112c]", "PID": 1712, "TID": 1768, "Arguments": [ "Arg1", "IN", "SIZE_T", "0x18feb0", "0x4e" ], "Timesptamp": "00000005.589709", "FunctionName": "malloc", "ModuleName": "msvcrt.dll", "Return": "0x3b2350", "Status": 0 }
{ "Address": "0x40b5e0", "Opcode": "ff152c114100", "Opcodesize": 6, "Mnemonic": "call dword ptr [0x41112c]", "PID": 1712, "TID": 1768, "Arguments": [ "Arg1", "IN", "SIZE_T", "0x18fe9c", "0x70" ], "Timesptamp": "00000005.605004", "FunctionName": "malloc", "ModuleName": "msvcrt.dll", "Return": "0x3b23a8", "Status": 0 }
{ "Address": "0x40b5e0", "Opcode": "ff152c114100", "Opcodesize": 6, "Mnemonic": "call dword ptr [0x41112c]", "PID": 1712, "TID": 1768, "Arguments": [ "Arg1", "IN", "SIZE_T", "0x18feb0", "0x52" ], "Timesptamp": "00000005.635983", "FunctionName": "malloc", "ModuleName": "msvcrt.dll", "Return": "0x3b2420", "Status": 0 }
{ "Address": "0x40e8f3", "Opcode": "ff1548114100", "Opcodesize": 6, "Mnemonic": "call dword ptr [0x411148]", "PID": 1712, "TID": 1768, "Arguments": [ "Arg1", "IN", "VOID*", "0x18fed8", "0x3b23a8" ], "Timesptamp": "00000005.651899", "FunctionName": "free", "ModuleName": "msvcrt.dll", "Functionname": "_onexit", "Dllname": "msvcrt.dll", "Status": 1 }
{ "Address": "0x40ec8f", "Opcode": "ff1530114100", "Opcodesize": 6, "Mnemonic": "call dword ptr [0x411130]", "PID": 1712, "TID": 1768, "Functionname": "__p___initenv", "Dllname": "msvcrt.dll", "Status": 1 }
{ "Address": "0x401043", "Opcode": "ff15d0104100", "Opcodesize": 6, "Mnemonic": "call dword ptr [0x4110d0]", "PID": 1712, "TID": 1768, "Functionname": "SetConsoleCtrlHandler", "Dllname": "kernel32.dll", "Status": 1 }
{ "Address": "0x40b83f", "Opcode": "ff1584114100", "Opcodesize": 6, "Mnemonic": "call dword ptr [0x411184]", "PID": 1712, "TID": 1768, "Arguments": [ "Arg1", "IN", "CHAR*", "0x18fb5c", "\n7-Zip 3.12  Copyright (c) 1999-2003 Igor Pavlov  2003-12-10\n", "Arg2", "OUT", "FILE*", "0x18fb60", "0x76232920" ], "Timesptamp": "00000005.833844", "FunctionName": "fputs", "ModuleName": "msvcrt.dll", "Return": "0x0", "Output1": [ "0x76232920", "0x0" ], "Status": 0 }
{ "Address": "0x404076", "Opcode": "ff15e0104100", "Opcodesize": 6, "Mnemonic": "call dword ptr [0x4110e0]", "PID": 1712, "TID": 1768, "Arguments": [ ], "Timesptamp": "00000005.854904", "FunctionName": "GetCommandLineW", "ModuleName": "kernel32.dll", "Return": "\\Users\\lhs\\Exec\\telock_7z.exe ", "Status": 0 }
{ "Address": "0x40b5e0", "Opcode": "ff152c114100", "Opcodesize": 6, "Mnemonic": "call dword ptr [0x41112c]", "PID": 1712, "TID": 1768, "Arguments": [ "Arg1", "IN", "SIZE_T", "0x18fb30", "0x3e" ], "Timesptamp": "00000005.873575", "FunctionName": "malloc", "ModuleName": "msvcrt.dll", "Return": "0x3b23d8", "Status": 0 }
{ "Address": "0x40b5e0", "Opcode": "ff152c114100", "Opcodesize": 6, "Mnemonic": "call dword ptr [0x41112c]", "PID": 1712, "TID": 1768, "Arguments": [ "Arg1", "IN", "SIZE_T", "0x18faf8", "0x3e" ], "Timesptamp": "00000005.892470", "FunctionName": "malloc", "ModuleName": "msvcrt.dll", "Return": "0x3b3488", "Status": 0 }
{ "Address": "0x40b5e0", "Opcode": "ff152c114100", "Opcodesize": 6, "Mnemonic": "call dword ptr [0x41112c]", "PID": 1712, "TID": 1768, "Arguments": [ "Arg1", "IN", "SIZE_T", "0x18fae0", "0x20" ], "Timesptamp": "00000005.908224", "FunctionName": "malloc", "ModuleName": "msvcrt.dll", "Return": "0x3b1338", "Status": 0 }
{ "Address": "0x409b63", "Opcode": "ff1504114100", "Opcodesize": 6, "Mnemonic": "call dword ptr [0x411104]", "PID": 1712, "TID": 1768, "Arguments": [ "Arg1", "IN", "VOID*", "0x18facc", "0x3b34c2", "Arg2", "IN", "ARRAY0", "0x18fad0", "ARRAY_0x2", "Arg3", "IN", "DWORD", "0x18fad4", "0x2" ], "Timesptamp": "00000005.929373", "FunctionName": "memmove", "ModuleName": "msvcrt.dll", "Return": "0x3b34c2", "Status": 0 }
{ "Address": "0x40b5e0", "Opcode": "ff152c114100", "Opcodesize": 6, "Mnemonic": "call dword ptr [0x41112c]", "PID": 1712, "TID": 1768, "Arguments": [ "Arg1", "IN", "SIZE_T", "0x18fae0", "0x20" ], "Timesptamp": "00000005.964337", "FunctionName": "malloc", "ModuleName": "msvcrt.dll", "Return": "0x3b1338", "Status": 0 }
{ "Address": "0x40b5e0", "Opcode": "ff152c114100", "Opcodesize": 6, "Mnemonic": "call dword ptr [0x41112c]", "PID": 1712, "TID": 1768, "Arguments": [ "Arg1", "IN", "SIZE_T", "0x18fb08", "0x20" ], "Timesptamp": "00000005.995994", "FunctionName": "malloc", "ModuleName": "msvcrt.dll", "Return": "0x3b1338", "Status": 0 }
{ "Address": "0x40b5e0", "Opcode": "ff152c114100", "Opcodesize": 6, "Mnemonic": "call dword ptr [0x41112c]", "PID": 1712, "TID": 1768, "Arguments": [ "Arg1", "IN", "SIZE_T", "0x18fb08", "0x20" ], "Timesptamp": "00000006.011426", "FunctionName": "malloc", "ModuleName": "msvcrt.dll", "Return": "0x3b34d0", "Status": 0 }
{ "Address": "0x40b5e0", "Opcode": "ff152c114100", "Opcodesize": 6, "Mnemonic": "call dword ptr [0x41112c]", "PID": 1712, "TID": 1768, "Arguments": [ "Arg1", "IN", "SIZE_T", "0x18fab0", "0x42" ], "Timesptamp": "00000006.025172", "FunctionName": "malloc", "ModuleName": "msvcrt.dll", "Return": "0x3b34f8", "Status": 0 }
{ "Address": "0x40b5e0", "Opcode": "ff152c114100", "Opcodesize": 6, "Mnemonic": "call dword ptr [0x41112c]", "PID": 1712, "TID": 1768, "Arguments": [ "Arg1", "IN", "SIZE_T", "0x18fa80", "0x20" ], "Timesptamp": "00000006.060390", "FunctionName": "malloc", "ModuleName": "msvcrt.dll", "Return": "0x3b1338", "Status": 0 }
{ "Address": "0x40b5e0", "Opcode": "ff152c114100", "Opcodesize": 6, "Mnemonic": "call dword ptr [0x41112c]", "PID": 1712, "TID": 1768, "Arguments": [ "Arg1", "IN", "SIZE_T", "0x18fa80", "0x2" ], "Timesptamp": "00000006.076087", "FunctionName": "malloc", "ModuleName": "msvcrt.dll", "Return": "0x3b3548", "Status": 0 }
{ "Address": "0x40b5e0", "Opcode": "ff152c114100", "Opcodesize": 6, "Mnemonic": "call dword ptr [0x41112c]", "PID": 1712, "TID": 1768, "Arguments": [ "Arg1", "IN", "SIZE_T", "0x18fa70", "0x2" ], "Timesptamp": "00000006.108906", "FunctionName": "malloc", "ModuleName": "msvcrt.dll", "Return": "0x3b1338", "Status": 0 }
{ "Address": "0x40b5e0", "Opcode": "ff152c114100", "Opcodesize": 6, "Mnemonic": "call dword ptr [0x41112c]", "PID": 1712, "TID": 1768, "Arguments": [ "Arg1", "IN", "SIZE_T", "0x18fac0", "0x2" ], "Timesptamp": "00000006.135209", "FunctionName": "malloc", "ModuleName": "msvcrt.dll", "Return": "0x3b1348", "Status": 0 }
{ "Address": "0x40b5e0", "Opcode": "ff152c114100", "Opcodesize": 6, "Mnemonic": "call dword ptr [0x41112c]", "PID": 1712, "TID": 1768, "Arguments": [ "Arg1", "IN", "SIZE_T", "0x18fae0", "0x20" ], "Timesptamp": "00000006.194703", "FunctionName": "malloc", "ModuleName": "msvcrt.dll", "Return": "0x3b34d0", "Status": 0 }
{ "Address": "0x40b5e0", "Opcode": "ff152c114100", "Opcodesize": 6, "Mnemonic": "call dword ptr [0x41112c]", "PID": 1712, "TID": 1768, "Arguments": [ "Arg1", "IN", "SIZE_T", "0x18fae0", "0x20" ], "Timesptamp": "00000006.238032", "FunctionName": "malloc", "ModuleName": "msvcrt.dll", "Return": "0x3b34d0", "Status": 0 }
{ "Address": "0x40b5e0", "Opcode": "ff152c114100", "Opcodesize": 6, "Mnemonic": "call dword ptr [0x41112c]", "PID": 1712, "TID": 1768, "Arguments": [ "Arg1", "IN", "SIZE_T", "0x18fae0", "0x20" ], "Timesptamp": "00000006.276222", "FunctionName": "malloc", "ModuleName": "msvcrt.dll", "Return": "0x3b34d0", "Status": 0 }
{ "Address": "0x40b5e0", "Opcode": "ff152c114100", "Opcodesize": 6, "Mnemonic": "call dword ptr [0x41112c]", "PID": 1712, "TID": 1768, "Arguments": [ "Arg1", "IN", "SIZE_T", "0x18fae0", "0x20" ], "Timesptamp": "00000006.319059", "FunctionName": "malloc", "ModuleName": "msvcrt.dll", "Return": "0x3b34d0", "Status": 0 }
{ "Address": "0x40b5e0", "Opcode": "ff152c114100", "Opcodesize": 6, "Mnemonic": "call dword ptr [0x41112c]", "PID": 1712, "TID": 1768, "Arguments": [ "Arg1", "IN", "SIZE_T", "0x18fafc", "0xc" ], "Timesptamp": "00000006.362843", "FunctionName": "malloc", "ModuleName": "msvcrt.dll", "Return": "0x3b34d0", "Status": 0 }
{ "Address": "0x40b5e0", "Opcode": "ff152c114100", "Opcodesize": 6, "Mnemonic": "call dword ptr [0x41112c]", "PID": 1712, "TID": 1768, "Arguments": [ "Arg1", "IN", "SIZE_T", "0x18fad8", "0x3c" ], "Timesptamp": "00000006.381990", "FunctionName": "malloc", "ModuleName": "msvcrt.dll", "Return": "0x3b3548", "Status": 0 }
{ "Address": "0x40b5e0", "Opcode": "ff152c114100", "Opcodesize": 6, "Mnemonic": "call dword ptr [0x41112c]", "PID": 1712, "TID": 1768, "Arguments": [ "Arg1", "IN", "SIZE_T", "0x18fad4", "0x10" ], "Timesptamp": "00000006.401297", "FunctionName": "malloc", "ModuleName": "msvcrt.dll", "Return": "0x3b3590", "Status": 0 }
{ "Address": "0x40bda5", "Opcode": "ff1504114100", "Opcodesize": 6, "Mnemonic": "call dword ptr [0x411104]", "PID": 1712, "TID": 1768, "Arguments": [ "Arg1", "IN", "VOID*", "0x18fad4", "0x3b3590", "Arg2", "IN", "ARRAY0", "Arg3", "IN", "DWORD", "0x18fadc", "0x0" ], "Timesptamp": "00000006.425340", "FunctionName": "memmove", "ModuleName": "msvcrt.dll", "Return": "0x3b3590", "Status": 0 }
{ "Address": "0x40b83f", "Opcode": "ff1584114100", "Opcodesize": 6, "Mnemonic": "call dword ptr [0x411184]", "PID": 1712, "TID": 1768, "Arguments": [ "Arg1", "IN", "CHAR*", "0x18fb58", "\nUsage: 7z <command> [<switches>...] <archive_name> [<file_names>...]\n       [<@listfiles...>]\n\n<Commands>\n  a: Add files to archive\n  d: Delete files from archive\n  e: Extract files from archive\n  l: List contents of archive\n  t: Test integrity of archive\n  u: Update files to archive\n  x: eXtract files with full pathname\n<Switches>\n  -bd Disable percentage indicator\n  -i[r[-|0]]{@listfile|!wildcard}: Include filenames\n  -m{Parameters}: set compression Method\n  -o{Directory}: set Output directory\n  -p{Password}: set Password\n  -r[-|0]: Recurse subdirectories\n  -sfx[{name}]: Create SFX archive\n  -t{Type}: Set type of archive\n  -u[-][p#][q#][r#][x#][y#][z#][!newArchiveName]: Update options\n  -w[{path}]: assign Work directory. Empty path means a temporary directory\n  -x[r[-|0]]]{@listfile|!wildcard}: eXclude filenames\n  -y: assume Yes on all queries\n", "Arg2", "OUT", "FILE*", "0x18fb5c", "0x76232920" ], "Timesptamp": "00000006.550134", "FunctionName": "fputs", "ModuleName": "msvcrt.dll", "Return": "0x0", "Output1": [ "0x76232920", "0x0" ], "Status": 0 }
{ "Address": "0x40bde5", "Opcode": "ff1504114100", "Opcodesize": 6, "Mnemonic": "call dword ptr [0x411104]", "PID": 1712, "TID": 1768, "Arguments": [ "Arg1", "IN", "VOID*", "0x18fb20", "0x3b3590", "Arg2", "IN", "ARRAY0", "Arg3", "IN", "DWORD", "0x18fb28", "0x0" ], "Timesptamp": "00000006.612727", "FunctionName": "memmove", "ModuleName": "msvcrt.dll", "Return": "0x3b3590", "Status": 0 }
{ "Address": "0x4010a9", "Opcode": "ff15d0104100", "Opcodesize": 6, "Mnemonic": "call dword ptr [0x4110d0]", "PID": 1712, "TID": 1768, "Arguments": [ "Arg1", "IN", "VOID*", "0x18fb60", "0x3b3590" ], "Timesptamp": "00000006.631329", "FunctionName": "free", "ModuleName": "msvcrt.dll", "Functionname": "SetConsoleCtrlHandler", "Dllname": "kernel32.dll", "Status": 1 }
{ "Address": "0x405cb9", "Opcode": "ff15c4114100", "Opcodesize": 6, "Mnemonic": "call dword ptr [0x4111c4]", "PID": 1712, "TID": 1768, "Functionname": "CoUninitialize", "Dllname": "ole32.dll", "Status": 1 }
{ "Address": "0x40ecaf", "Opcode": "ff1534114100", "Opcodesize": 6, "Mnemonic": "call dword ptr [0x411134]", "PID": 1712, "TID": 1768, "Arguments": [ "Arg1", "IN", "INT", "0x18ff48", "0x0" ], "Timesptamp": "00000006.711575", "FunctionName": "exit", "ModuleName": "msvcrt.dll" }
